dataviz/__init__.py
dataviz/core.py
ml_dataviz-0.1.0.dist-info/licenses/LICENSE
ml_dataviz-0.1.0.dist-info/METADATA
ml_dataviz-0.1.0.dist-info/WHEEL
ml_dataviz-0.1.0.dist-info/top_level.txt
ml_dataviz-0.1.0.dist-info/RECORD
