Metadata-Version: 2.4
Name: ml-dataviz
Version: 0.1.0
Summary: Data Visualization and Insight Library
Author: Hsinghsudwal
Requires-Python: >=3.10
License-File: LICENSE
Requires-Dist: ipython
Requires-Dist: jupyter
Requires-Dist: matplotlib
Requires-Dist: numpy
Requires-Dist: pandas
Requires-Dist: seaborn
Dynamic: license-file
